odoo10_addon_sale_order_lot_generator-10.0.0.0.2-py3.8-nspkg.pth
odoo/addons/sale_order_lot_generator/README.rst
odoo/addons/sale_order_lot_generator/__init__.py
odoo/addons/sale_order_lot_generator/__manifest__.py
odoo/addons/sale_order_lot_generator/i18n/ca.po
odoo/addons/sale_order_lot_generator/i18n/de.po
odoo/addons/sale_order_lot_generator/i18n/el_GR.po
odoo/addons/sale_order_lot_generator/i18n/es.po
odoo/addons/sale_order_lot_generator/i18n/es_ES.po
odoo/addons/sale_order_lot_generator/i18n/es_VE.po
odoo/addons/sale_order_lot_generator/i18n/fi.po
odoo/addons/sale_order_lot_generator/i18n/fr.po
odoo/addons/sale_order_lot_generator/i18n/hr.po
odoo/addons/sale_order_lot_generator/i18n/hr_HR.po
odoo/addons/sale_order_lot_generator/i18n/hu.po
odoo/addons/sale_order_lot_generator/i18n/it.po
odoo/addons/sale_order_lot_generator/i18n/nl.po
odoo/addons/sale_order_lot_generator/i18n/nl_NL.po
odoo/addons/sale_order_lot_generator/i18n/pt.po
odoo/addons/sale_order_lot_generator/i18n/pt_BR.po
odoo/addons/sale_order_lot_generator/i18n/ro.po
odoo/addons/sale_order_lot_generator/i18n/sale_order_lot_generator.pot
odoo/addons/sale_order_lot_generator/i18n/sk.po
odoo/addons/sale_order_lot_generator/i18n/sl.po
odoo/addons/sale_order_lot_generator/i18n/tr.po
odoo/addons/sale_order_lot_generator/i18n/tr_TR.po
odoo/addons/sale_order_lot_generator/i18n/vi_VN.po
odoo/addons/sale_order_lot_generator/i18n/zh_CN.po
odoo/addons/sale_order_lot_generator/models/__init__.py
odoo/addons/sale_order_lot_generator/models/product.py
odoo/addons/sale_order_lot_generator/models/sale.py
odoo/addons/sale_order_lot_generator/static/description/icon.png
odoo/addons/sale_order_lot_generator/tests/__init__.py
odoo/addons/sale_order_lot_generator/tests/test_sale_order_lot_generator.py
odoo/addons/sale_order_lot_generator/views/product_view.xml
odoo10_addon_sale_order_lot_generator-10.0.0.0.2.dist-info/METADATA
odoo10_addon_sale_order_lot_generator-10.0.0.0.2.dist-info/WHEEL
odoo10_addon_sale_order_lot_generator-10.0.0.0.2.dist-info/namespace_packages.txt
odoo10_addon_sale_order_lot_generator-10.0.0.0.2.dist-info/top_level.txt
odoo10_addon_sale_order_lot_generator-10.0.0.0.2.dist-info/RECORD
