Metadata-Version: 2.1
Name: odoo10-addon-sale-order-lot-generator
Version: 10.0.0.0.2
Summary: sale_order_lot_generator
Home-page: https://github.com/OCA/sale-workflow
Author: Akretion, Odoo Community Association (OCA)
Author-email: support@odoo-community.org
License: AGPL-3
Platform: UNKNOWN
Classifier: Programming Language :: Python
Classifier: Framework :: Odoo
Classifier: Framework :: Odoo :: 10.0
Classifier: License :: OSI Approved :: GNU Affero General Public License v3
Requires-Python: ~=2.7
Requires-Dist: odoo10-addon-sale-order-lot-selection
Requires-Dist: odoo (<10.1dev,>=10.0)
